__init__.py
omicsone_diff/main.py
omicsone_diff/plugins/diff.cp39-win_amd64.pyd
omicsone_diff/plugins/param.cp39-win_amd64.pyd
omicsone_diff-0.1.0.dist-info/LICENSE
omicsone_diff-0.1.0.dist-info/METADATA
omicsone_diff-0.1.0.dist-info/WHEEL
omicsone_diff-0.1.0.dist-info/entry_points.txt
omicsone_diff-0.1.0.dist-info/top_level.txt
omicsone_diff-0.1.0.dist-info/RECORD
